<annotation>
	<folder>Fire</folder>
	<filename>F_158.jpg</filename>
	<path>C:\Users\User\Desktop\archive (6)\Data\Train_Data\Fire\F_158.jpg</path>
	<source>
		<database>Unknown</database>
	</source>
	<size>
		<width>250</width>
		<height>250</height>
		<depth>3</depth>
	</size>
	<segmented>0</segmented>
	<object>
		<name>fire</name>
		<pose>Unspecified</pose>
		<truncated>1</truncated>
		<difficult>0</difficult>
		<bndbox>
			<xmin>1</xmin>
			<ymin>123</ymin>
			<xmax>121</xmax>
			<ymax>218</ymax>
		</bndbox>
	</object>
	<object>
		<name>fire</name>
		<pose>Unspecified</pose>
		<truncated>1</truncated>
		<difficult>0</difficult>
		<bndbox>
			<xmin>168</xmin>
			<ymin>102</ymin>
			<xmax>250</xmax>
			<ymax>244</ymax>
		</bndbox>
	</object>
	<object>
		<name>fire</name>
		<pose>Unspecified</pose>
		<truncated>0</truncated>
		<difficult>0</difficult>
		<bndbox>
			<xmin>138</xmin>
			<ymin>164</ymin>
			<xmax>169</xmax>
			<ymax>196</ymax>
		</bndbox>
	</object>
</annotation>
